[
  {
    "ContainingType": "EmployeeA.Controllers.EmployeeAPIController",
    "Method": "Get",
    "RelativePath": "api/EmployeeAPI",
    "HttpMethod": "GET",
    "IsController": true,
    "Order": 0,
    "Parameters": [],
    "ReturnTypes": [
      {
        "Type": "System.Collections.Generic.List\u00601[[EmployeeA.Models.Employee, EmployeeA, Version=1.0.0.0, Culture=neutral, PublicKeyToken=null]]",
        "MediaTypes": [
          "text/plain",
          "application/json",
          "text/json"
        ],
        "StatusCode": 200
      }
    ]
  },
  {
    "ContainingType": "EmployeeA.Controllers.EmployeeAPIController",
    "Method": "Create",
    "RelativePath": "api/EmployeeAPI",
    "HttpMethod": "POST",
    "IsController": true,
    "Order": 0,
    "Parameters": [
      {
        "Name": "employee",
        "Type": "EmployeeA.Models.Employee",
        "IsRequired": true
      }
    ],
    "ReturnTypes": [
      {
        "Type": "EmployeeA.Models.Employee",
        "MediaTypes": [
          "text/plain",
          "application/json",
          "text/json"
        ],
        "StatusCode": 200
      }
    ]
  },
  {
    "ContainingType": "EmployeeA.Controllers.EmployeeAPIController",
    "Method": "GetbyID",
    "RelativePath": "api/EmployeeAPI/{id}",
    "HttpMethod": "GET",
    "IsController": true,
    "Order": 0,
    "Parameters": [
      {
        "Name": "id",
        "Type": "System.Int32",
        "IsRequired": true
      }
    ],
    "ReturnTypes": [
      {
        "Type": "EmployeeA.Models.Employee",
        "MediaTypes": [
          "text/plain",
          "application/json",
          "text/json"
        ],
        "StatusCode": 200
      }
    ]
  }
]